Workbook

Sheet Roblox SkatePark + Olympics
B2: Game design and operations
B3: Development | C3: 120000 | D3: one-time | E3: A Look At Roblox Developer Unit Economics — Naavik
B4: Production support | C4: 20 | D4: annual
B6: Athlete funnel
B7: Number of athletes | C7: 4
B8: Annual retainer per person | C8: 20000
B9: Total annual retainer | C9: =C7*C8 -> 80000
B11: Cybersmile
B12: Per hour charge | C12: 10
B13: Hours/day | C13: 9
C14: 2023 | D14: 2024 | E14: 2025 | F14: 2026 | G14: 2027 | H14: 2028 | I14: 2029
B15: # Moderators | C15: =C22/($J$15*$M$30) -> 1.5 | D15: =D22/($J$15*$M$30) -> 18 | E15: =E22/($J$15*$M$30) -> 6 | F15: =F22/($J$15*$M$30) -> 7.2 | G15: =G22/($J$15*$M$30) -> 9 | H15: =H22/($J$15*$M$30) -> 30 | I15: =I22/($J$15*$M$30) -> 10.5 | J15: 5000 | K15: Users:Moderators ratio
B16: Moderator costs | C16: =C15*$C$13*$C$12*365 -> 49275 | D16: =D15*$C$13*$C$12*365 -> 591300 | E16: =E15*$C$13*$C$12*365 -> 197100 | F16: =F15*$C$13*$C$12*365 -> 236520 | G16: =G15*$C$13*$C$12*365 -> 295650 | H16: =H15*$C$13*$C$12*365 -> 985500 | I16: =I15*$C$13*$C$12*365 -> 344925
B17: Moderator hours | C17: =C15*$C$13*365 -> 4927.5 | D17: =D15*$C$13*365 -> 59130 | E17: =E15*$C$13*365 -> 19710 | F17: =F15*$C$13*365 -> 23652 | G17: =G15*$C$13*365 -> 29565 | H17: =H15*$C$13*365 -> 98550 | I17: =I15*$C$13*365 -> 34492.5 | J17: =SUM(C17:I17) -> 270027 | K17: =H17/365 -> 270
B18: Total expense | C18: =C3+C4+C16+C9 -> 249295 | D18: =D16+$C$4+$C$9 -> 671320 | E18: =E16+$C$4+$C$9 -> 277120 | F18: =F16+$C$4+$C$9 -> 316540 | G18: =G16+$C$4+$C$9 -> 375670 | H18: =H16+$C$4+$C$9 -> 1065520 | I18: =I16+$C$4+$C$9 -> 424945
L20: VansWorld
C21: 2023 | D21: 2024 | E21: 2025 | F21: 2026 | G21: 2027 | H21: 2028 | I21: 2029 | L21: Years | M21: 2
B22: Players (MAU) | C22: 50000 | D22: 600000 | E22: 200000 | F22: 240000 | G22: 300000 | H22: 1000000 | I22: 350000 | L22: Favs | M22: 617
B23: Shoppers | C23: =C22*$C$29 -> 2500 | D23: =D22*$C$29 -> 30000 | E23: =E22*$C$29 -> 10000 | F23: =F22*$C$29 -> 12000 | G23: =G22*$C$29 -> 15000 | H23: =H22*$C$29 -> 50000 | I23: =I22*$C$29 -> 17500 | L23: Visits | M23: 91200
B24: Revenue driven | C24: =C23*$C$30 -> 227700 | D24: =D23*$C$30 -> 2732400 | E24: =E23*$C$30 -> 910800 | F24: =F23*$C$30 -> 1092960 | G24: =G23*$C$30 -> 1366200 | H24: =H23*$C$30 -> 4554000 | I24: =I23*$C$30 -> 1593900 | L24: Visits/fav | M24: =M23/M22 -> 147.81199
B25: Operating profits driven | C25: =C24*'Influencer Campaign'!$I$6 -> 68310 | D25: =D24*'Influencer Campaign'!$I$6 -> 819720 | E25: =E24*'Influencer Campaign'!$I$6 -> 273240 | F25: =F24*'Influencer Campaign'!$I$6 -> 327888 | G25: =G24*'Influencer Campaign'!$I$6 -> 409860 | H25: =H24*'Influencer Campaign'!$I$6 -> 1366200 | I25: =I24*'Influencer Campaign'!$I$6 -> 478170 | L25: Now playing | M25: 0.42
L26: Average play time | M26: 0.5
B27: Campaign attributable profits | C27: =C25-C18 -> -180985 | D27: =D25-D18 -> 148400 | E27: =E25-E18 -> -3880 | F27: =F25-F18 -> 11348 | G27: =G25-G18 -> 34190 | H27: =H25-H18 -> 300680 | I27: =I25-I18 -> 53225 | J27: =SUM(C27:I27) -> 362978
L28: DAU | M28: =M25*12/M26 -> 10.08
B29: % shoppers | C29: 0.05 | L29: DAU/MAU | M29: 0.15
B30: ARPU | C30: ='Influencer Campaign'!L35 -> 91.08 | L30: MAU/DAU | M30: =1/M29 -> 6.6666667
C31: Total (7 years) | D31: Average annual | L31: MAU | M31: =M28*M30 -> 67.2
B32: Total revenue from campaign | C32: =SUM(C24:I24) -> 12477960 | D32: =C32/7 -> 1782565.7
B33: Total expense | C33: =SUM(C18:I18) -> 3380410 | D33: =C33/7 -> 482915.71
B34: Marketing RoI | C34: =C32/C33 -> 3.6912564 | D34: https://www.rhythminfluence.com/influencer-marketing-roi-and-analytics
B35: Average op profits | D35: =SUM(C25:I25)/7 -> 534769.71

Sheet Influencer Campaign
D1: 1 | E1: 2 | F1: 3 | G1: 4 | H1: 5
C2: 2023 | D2: 2024 | E2: 2025 | F2: 2026 | G2: 2027 | H2: 2028
B4: New customers | C4: =H27*C29*C30 -> 26752.5 | D4: =C4*$C$35 -> 4012.875 | E4: =D4*$C$35 -> 601.93125 | F4: =E4*$C$35 -> 90.289687 | G4: =F4*$C$35 -> 13.543453 | H4: =G4*$C$35 -> 2.031518
B5: LTV generated | C5: =C4*$L$37 -> 3045772.1 | D5: =D4*$L$37 -> 456865.82 | E5: =E4*$L$37 -> 68529.873 | F5: =F4*$L$37 -> 10279.481 | G5: =G4*$L$37 -> 1541.9221 | H5: =H4*$L$37 -> 231.28832
B6: Gross profit | C6: =C5*$I$6 -> 913731.64 | D6: =D5*$I$6 -> 137059.75 | E6: =E5*$I$6 -> 20558.962 | F6: =F5*$I$6 -> 3083.8443 | G6: =G5*$I$6 -> 462.57664 | H6: =H5*$I$6 -> 69.386496 | I6: 0.3 | J6: https://www.freelanceformulations.com/post/what-is-the-average-profit-margin-of-the-cosmetic-industry
B7: Total profit | C7: =SUM(C6:H6) -> 1074966.2
B8: Total revenue | C8: =SUM(C5:H5) -> 3583220.5 | D8: =C8/4 -> 895805.13
B10: Marketing Costs | D10: Annual
B11: Influencer costs | C11: =L27 -> 270000
B12: Content strategy | C12: =H34*12 -> 60000
B13: Offline marketing campaign | C13: 100000
B14: Net expense | C14: =SUM(C11:C13) -> 430000
B16: Marketing RoI | C16: =C8/C14 -> 8.3330709
M18: `
B20: Influencer rates | G20: Influencer | H20: Followers | I20: Tier | J20: Rate | K20: Posts | L20: Cost
C21: Followers | D21: Per post rate | G21: Bryce Wettstein | H21: 51900 | I21: Micro | J21: =$D$23 -> 1500 | K21: =$H$33 -> 20 | L21: =J21*K21 -> 30000
B22: Nano | C22: 5000 | D22: 800 | G22: Alexis Sablone | H22: 92400 | I22: Micro | J22: =$D$23 -> 1500 | K22: =$H$33 -> 20 | L22: =J22*K22 -> 30000
B23: Micro | C23: 30000 | D23: 1500 | G23: Jordyn Barratt | H23: 42200 | I23: Micro | J23: =$D$23 -> 1500 | K23: =$H$33 -> 20 | L23: =J23*K23 -> 30000
B24: Mid-tier | C24: 200000 | D24: 3000 | G24: Brighton Zeuner | H24: 155000 | I24: Mid-tier | J24: =$D$24 -> 3000 | K24: =$H$33 -> 20 | L24: =J24*K24 -> 60000
B25: Macro | C25: 800000 | D25: 5000 | G25: Mariah Duran | H25: 153000 | I25: Mid-tier | J25: =$D$24 -> 3000 | K25: =$H$33 -> 20 | L25: =J25*K25 -> 60000
B26: Mega | C26: 2000000 | D26: 7000 | G26: Alana Smith | H26: 100000 | I26: Mid-tier | J26: =$D$24 -> 3000 | K26: =$H$33 -> 20 | L26: =J26*K26 -> 60000
G27: Total | H27: =SUM(H21:H26) -> 594500 | L27: =SUM(L21:L26) -> 270000
B29: Lead generation | C29: 0.15 | J29: LTV
B30: Lead conversion | C30: 0.3 | J30: Monthly spend on beauty, fitness, wellness
L31: 110 | M31: https://www.salontoday.com/1082057/new-study-evaluates-american-spending-on-beauty-fitness-and-wellness
B32: CAC | C32: =C14/C4 -> 16.073264 | G32: Content | J32: Facial skin care | L32: 0.23
G33: Number of posts | H33: 20 | J33: % captured by UD | L33: 0.3
B34: LTV/CAC | C34: =L37/C32 -> 7.083191 | G34: Content strategy cost (monthly) | H34: 5000 | J34: UD monthly revenue | L34: =L31*L32*L33 -> 7.59
B35: Follower growth rate | C35: 0.15 | J35: UD annual revenue | L35: =L34*12 -> 91.08
J36: Annual churn | L36: 0.2
J37: LTV | L37: =L35/(1-L36) -> 113.85
B40: GutCheck
B41: Revenue | C41: 32000000000
B42: Loreal | C42: =3%*C41 -> 960000000
B43: Profit | C43: =C42*20% -> 192000000
